README.rst
setup.py
src/zc/__init__.py
src/zc.wsgirunner.egg-info/PKG-INFO
src/zc.wsgirunner.egg-info/SOURCES.txt
src/zc.wsgirunner.egg-info/dependency_links.txt
src/zc.wsgirunner.egg-info/entry_points.txt
src/zc.wsgirunner.egg-info/namespace_packages.txt
src/zc.wsgirunner.egg-info/not-zip-safe
src/zc.wsgirunner.egg-info/requires.txt
src/zc.wsgirunner.egg-info/top_level.txt
src/zc/wsgirunner/__init__.py
src/zc/wsgirunner/main.test
src/zc/wsgirunner/tests.py