Metadata-Version: 1.0
Name: zc.wsgirunner
Version: 0.1.0
Summary: ************************************************************
Home-page: UNKNOWN
Author: Jim Fulton
Author-email: jim@zope.com
License: ZPL 2.1
Platform: UNKNOWN
